Metadata-Version: 2.4
Name: llama-index-packs-chroma-autoretrieval
Version: 0.4.1
Summary: llama-index packs chroma_autoretrieval integration
Author-email: Your Name <you@example.com>
Maintainer: logan-markewich
License-Expression: MIT
License-File: LICENSE
Keywords: chroma,retrieval,vector
Requires-Python: <4.0,>=3.10
Requires-Dist: llama-index-core<0.15,>=0.13.0
Requires-Dist: llama-index-vector-stores-chroma<0.6,>=0.5.0
